xypyutil.py
xypyutil-1.0.9.dist-info/LICENSE
xypyutil-1.0.9.dist-info/METADATA
xypyutil-1.0.9.dist-info/WHEEL
xypyutil-1.0.9.dist-info/RECORD
