Metadata-Version: 2.3
Name: xypyutil
Version: 1.0.9
Summary: Building blocks for sysadmin and DevOps
License: MIT
Keywords: utility,logging,systems
Author: Xi Ye
Author-email: zcyh147@gmail.com
Maintainer: Xi Ye
Maintainer-email: zcyh147@gmail.com
Requires-Python: >=3.9,<4.0
Classifier: License :: OSI Approved :: MIT License
Classifier: Programming Language :: Python :: 3
Classifier: Programming Language :: Python :: 3.9
Classifier: Programming Language :: Python :: 3.10
Classifier: Programming Language :: Python :: 3.11
Classifier: Programming Language :: Python :: 3.12
Classifier: Programming Language :: Python :: 3.13
Project-URL: Documentation, https://github.com/zcyh147/xypyutil/README.md
Project-URL: Homepage, https://github.com/zcyh147/xypyutil/
Project-URL: Repository, https://github.com/zcyh147/xypyutil/
Project-URL: issues, https://github.com/zcyh147/xypyutil//issues
